Products.PloneLDAP-2.0.0a1-py3.10-nspkg.pth
Products/PloneLDAP/__init__.py
Products/PloneLDAP/_utils.py
Products/PloneLDAP/configure.zcml
Products/PloneLDAP/factory.py
Products/PloneLDAP/products.py
Products/PloneLDAP/property.py
Products/PloneLDAP/version.txt
Products/PloneLDAP/mixins/__init__.py
Products/PloneLDAP/mixins/groupcaps.py
Products/PloneLDAP/mixins/groupintro.py
Products/PloneLDAP/mixins/groupmgmt.py
Products/PloneLDAP/mixins/useradder.py
Products/PloneLDAP/mixins/usermgmt.py
Products/PloneLDAP/mixins/userprops.py
Products/PloneLDAP/plugins/__init__.py
Products/PloneLDAP/plugins/ad.py
Products/PloneLDAP/plugins/base.py
Products/PloneLDAP/plugins/ldap.py
Products/PloneLDAP/tests/__init__.py
Products/PloneLDAP/tests/integrationcase.py
Products/PloneLDAP/tests/testCreation.py
Products/PloneLDAP/tests/testInterfaces.py
Products/PloneLDAP/www/addAdPlugin.zpt
Products/PloneLDAP/www/addLdapPlugin.zpt
Products/PloneLDAP/www/admultiplugin.png
Products/PloneLDAP/www/ldapmultiplugin.png
Products.PloneLDAP-2.0.0a1.dist-info/METADATA
Products.PloneLDAP-2.0.0a1.dist-info/WHEEL
Products.PloneLDAP-2.0.0a1.dist-info/namespace_packages.txt
Products.PloneLDAP-2.0.0a1.dist-info/top_level.txt
Products.PloneLDAP-2.0.0a1.dist-info/RECORD
