Metadata-Version: 2.1
Name: Products.PloneLDAP
Version: 2.0.0a1
Summary: LDAP/Active Directory support for Plone
Home-page: https://github.com/collective/Products.PloneLDAP
Author: Wichert Akkerman - Simpon
Author-email: wichert@simplon.biz
License: Zope Public License 2.1
Keywords: Zope CMF Plone LDAP authentication
Classifier: Framework :: Plone
Classifier: Framework :: Zope2
Classifier: Programming Language :: Python
Classifier: Topic :: Software Development :: Libraries :: Python Modules
Classifier: Topic :: System :: Systems Administration :: Authentication/Directory :: LDAP
Classifier: License :: OSI Approved :: Zope Public License
Requires-Dist: setuptools
Requires-Dist: Products.PlonePAS
Requires-Dist: Products.LDAPMultiPlugins
Requires-Dist: Products.LDAPUserFolder
